strawberry_django_jwt/__init__.py
strawberry_django_jwt/auth.py
strawberry_django_jwt/backends.py
strawberry_django_jwt/decorators.py
strawberry_django_jwt/exceptions.py
strawberry_django_jwt/fields.py
strawberry_django_jwt/locale/ar/LC_MESSAGES/django.mo
strawberry_django_jwt/locale/ar/LC_MESSAGES/django.po
strawberry_django_jwt/locale/es/LC_MESSAGES/django.mo
strawberry_django_jwt/locale/es/LC_MESSAGES/django.po
strawberry_django_jwt/locale/fr/LC_MESSAGES/django.mo
strawberry_django_jwt/locale/fr/LC_MESSAGES/django.po
strawberry_django_jwt/locale/nl/LC_MESSAGES/django.mo
strawberry_django_jwt/locale/nl/LC_MESSAGES/django.po
strawberry_django_jwt/locale/pt_BR/LC_MESSAGES/django.mo
strawberry_django_jwt/locale/pt_BR/LC_MESSAGES/django.po
strawberry_django_jwt/middleware.py
strawberry_django_jwt/mixins.py
strawberry_django_jwt/model_object_types.py
strawberry_django_jwt/mutations.py
strawberry_django_jwt/object_types.py
strawberry_django_jwt/path.py
strawberry_django_jwt/refresh_token/__init__.py
strawberry_django_jwt/refresh_token/admin/__init__.py
strawberry_django_jwt/refresh_token/admin/filters.py
strawberry_django_jwt/refresh_token/apps.py
strawberry_django_jwt/refresh_token/decorators.py
strawberry_django_jwt/refresh_token/locale/ar/LC_MESSAGES/django.mo
strawberry_django_jwt/refresh_token/locale/ar/LC_MESSAGES/django.po
strawberry_django_jwt/refresh_token/locale/es/LC_MESSAGES/django.mo
strawberry_django_jwt/refresh_token/locale/es/LC_MESSAGES/django.po
strawberry_django_jwt/refresh_token/locale/fr/LC_MESSAGES/django.mo
strawberry_django_jwt/refresh_token/locale/fr/LC_MESSAGES/django.po
strawberry_django_jwt/refresh_token/locale/nl/LC_MESSAGES/django.mo
strawberry_django_jwt/refresh_token/locale/nl/LC_MESSAGES/django.po
strawberry_django_jwt/refresh_token/locale/pt_BR/LC_MESSAGES/django.mo
strawberry_django_jwt/refresh_token/locale/pt_BR/LC_MESSAGES/django.po
strawberry_django_jwt/refresh_token/management/__init__.py
strawberry_django_jwt-0.2.1.dist-info/LICENSE
strawberry_django_jwt-0.2.1.dist-info/WHEEL
strawberry_django_jwt-0.2.1.dist-info/METADATA
strawberry_django_jwt-0.2.1.dist-info/RECORD
